grip/__init__.py
grip/grip.py
grip/metaclasses.py
grip_mbmasuda-0.1.1.dist-info/LICENSE
grip_mbmasuda-0.1.1.dist-info/METADATA
grip_mbmasuda-0.1.1.dist-info/WHEEL
grip_mbmasuda-0.1.1.dist-info/top_level.txt
grip_mbmasuda-0.1.1.dist-info/RECORD
