Metadata-Version: 2.1
Name: grip-mbmasuda
Version: 0.1.1
Summary: Generic rate-limited item processor
Home-page: https://github.com/mbmasuda/generic-rate-limited-item-processor
Author: Mari Masuda
Author-email: mbmasuda.github@gmail.com
License: UNKNOWN
Platform: UNKNOWN
Classifier: Programming Language :: Python :: 3
Classifier: License :: OSI Approved :: MIT License
Classifier: Operating System :: OS Independent
License-File: LICENSE
